nifty8/__init__.py
nifty8/config.py
nifty8/domain_tuple.py
nifty8/ducc_dispatch.py
nifty8/evidence_lower_bound.py
nifty8/extra.py
nifty8/field.py
nifty8/linearization.py
nifty8/logger.py
nifty8/multi_domain.py
nifty8/multi_field.py
nifty8/operator_spectrum.py
nifty8/operator_tree_optimiser.py
nifty8/plot.py
nifty8/pointwise.py
nifty8/probing.py
nifty8/random.py
nifty8/sugar.py
nifty8/utilities.py
nifty8/domains/__init__.py
nifty8/domains/dof_space.py
nifty8/domains/domain.py
nifty8/domains/gl_space.py
nifty8/domains/hp_space.py
nifty8/domains/lm_space.py
nifty8/domains/power_space.py
nifty8/domains/rg_space.py
nifty8/domains/structured_domain.py
nifty8/domains/unstructured_domain.py
nifty8/library/__init__.py
nifty8/library/adjust_variances.py
nifty8/library/correlated_fields.py
nifty8/library/correlated_fields_simple.py
nifty8/library/dynamic_operator.py
nifty8/library/light_cone_operator.py
nifty8/library/los_response.py
nifty8/library/nft.py
nifty8/library/special_distributions.py
nifty8/library/variational_models.py
nifty8/library/wiener_filter_curvature.py
nifty8/minimization/__init__.py
nifty8/minimization/conjugate_gradient.py
nifty8/minimization/descent_minimizers.py
nifty8/minimization/energy.py
nifty8/minimization/energy_adapter.py
nifty8/minimization/iteration_controllers.py
nifty8/minimization/kl_energies.py
nifty8/minimization/line_search.py
nifty8/minimization/minimizer.py
nifty8/minimization/nonlinear_cg.py
nifty8/minimization/optimize_kl.py
nifty8/minimization/quadratic_energy.py
nifty8/minimization/sample_list.py
nifty8/minimization/scipy_minimizer.py
nifty8/minimization/stochastic_minimizer.py
nifty8/minimization/config/__init__.py
nifty8/minimization/config/optimize_kl_config.py
nifty8/operators/__init__.py
nifty8/operators/adder.py
nifty8/operators/block_diagonal_operator.py
nifty8/operators/chain_operator.py
nifty8/operators/contraction_operator.py
nifty8/operators/convolution_operators.py
nifty8/operators/counting_operator.py
nifty8-8.5.7.dist-info/licenses/COPYING
nifty8-8.5.7.dist-info/METADATA
nifty8-8.5.7.dist-info/WHEEL
nifty8-8.5.7.dist-info/top_level.txt
nifty8-8.5.7.dist-info/RECORD
