Metadata-Version: 2.4
Name: nifty8
Version: 8.5.7
Summary: Probabilistic programming framework for signal inference algorithms that operate regardless of the underlying grids and their resolutions
Author-email: Martin Reinecke <martin@mpa-garching.mpg.de>
Project-URL: Homepage, https://github.com/nifty-ppl/nifty
Project-URL: Source Code, https://github.com/nifty-ppl/nifty
Project-URL: Bug Tracker, https://github.com/nifty-ppl/nifty/issues
Project-URL: Documentation, https://ift.pages.mpcdf.de/nifty/
Project-URL: Changelog, https://github.com/NIFTy-PPL/NIFTy/blob/NIFTy_8/ChangeLog.md
Classifier: Development Status :: 5 - Production/Stable
Classifier: Intended Audience :: Science/Research
Classifier: Topic :: Scientific/Engineering :: Mathematics
Classifier: Topic :: Scientific/Engineering :: Physics
Classifier: License :: OSI Approved :: GNU General Public License v3 (GPLv3)
Classifier: Operating System :: OS Independent
Classifier: Programming Language :: Python
Requires-Python: >=3.10
License-File: COPYING
Requires-Dist: numpy>=1.17.0
Requires-Dist: scipy>=1.9.0
Provides-Extra: re
Requires-Dist: jax; extra == "re"
Requires-Dist: jaxlib; extra == "re"
Requires-Dist: jaxbind; extra == "re"
Requires-Dist: ducc0>=0.27.0; extra == "re"
Provides-Extra: native
Requires-Dist: ducc0>=0.27.0; extra == "native"
Provides-Extra: parallel
Requires-Dist: mpi4py; extra == "parallel"
Provides-Extra: doc
Requires-Dist: sphinx<8.2; extra == "doc"
Requires-Dist: pydata-sphinx-theme; extra == "doc"
Requires-Dist: sphinxcontrib-bibtex; extra == "doc"
Requires-Dist: myst-parser; extra == "doc"
Requires-Dist: jupyter; extra == "doc"
Requires-Dist: nbconvert; extra == "doc"
Requires-Dist: jupytext; extra == "doc"
Provides-Extra: util
Requires-Dist: astropy; extra == "util"
Requires-Dist: healpy; extra == "util"
Requires-Dist: h5py; extra == "util"
Requires-Dist: matplotlib; extra == "util"
Provides-Extra: test
Requires-Dist: pytest; extra == "test"
Requires-Dist: pytest-cov; extra == "test"
Requires-Dist: pytest-xdist; extra == "test"
Requires-Dist: ducc0; extra == "test"
Requires-Dist: nifty8[re]; extra == "test"
Requires-Dist: nifty8[util]; extra == "test"
Provides-Extra: all
Requires-Dist: nifty8[doc,native,parallel,re,test,util]; extra == "all"
Dynamic: license-file
